{
	"name": "outputsql",
	"properties": {
		"linkedServiceName": {
			"referenceName": "AzureDataLakeStorage3",
			"type": "LinkedServiceReference"
		},
		"annotations": [],
		"type": "DelimitedText",
		"typeProperties": {
			"location": {
				"type": "AzureBlobFSLocation",
				"fileName": "outputsqlFile_parametered",
				"folderPath": "input1.1",
				"fileSystem": "project"
			},
			"columnDelimiter": ",",
			"escapeChar": "\\",
			"firstRowAsHeader": true,
			"quoteChar": "\""
		},
		"schema": []
	}
}